bxserum/__init__.py
bxserum/proto/__init__.py
bxserum/proto/api.py
bxserum/proto/google/__init__.py
bxserum/proto/google/api.py
bxserum/proto/grpc/__init__.py
bxserum/proto/grpc/gateway/__init__.py
bxserum/proto/grpc/gateway/protoc_gen_openapiv2/__init__.py
bxserum/proto/grpc/gateway/protoc_gen_openapiv2/options.py
bxserum/provider/__init__.py
bxserum/provider/base.py
bxserum/provider/constants.py
bxserum/provider/grpc.py
bxserum/provider/http.py
bxserum/provider/http_error.py
bxserum/provider/ws.py
bxserum/transaction/__init__.py
bxserum/transaction/deserializer.py
bxserum/transaction/signing.py
bxserum/transaction/signing_test.py
bxserum-1.0.0.dist-info/LICENSE
bxserum-1.0.0.dist-info/METADATA
bxserum-1.0.0.dist-info/WHEEL
bxserum-1.0.0.dist-info/top_level.txt
bxserum-1.0.0.dist-info/RECORD
