Metadata-Version: 2.1
Name: bxserum
Version: 1.0.0
Summary: Python SDK for bloXroute's Serum API
Home-page: https://github.com/bloXroute-Labs/serum-client-python
Author: bloXroute Labs
Author-email: support@bloxroute.com
Keywords: serum,solana,blockchain,trader,grpc,stream
Classifier: Programming Language :: Python :: 3
License-File: LICENSE
Requires-Dist: aiohttp (==3.8.1)
Requires-Dist: betterproto[compiler] (==1.2.5)
Requires-Dist: grpclib (==0.4.2)
Requires-Dist: aiounittest (==1.4.1)
Requires-Dist: base58 (==2.1.1)
Requires-Dist: solana (==0.23.3)
Requires-Dist: bx-jsonrpc-py (==0.1.0)
